Metadata-Version: 2.1
Name: yamspy
Version: 0.3.3
Summary: Yet Another Implementation of Multiwii Serial Protocol Python Interface for Betaflight, iNAV, etc.
Home-page: https://github.com/ricardodeazambuja/YAMSPy
Author: Ricardo de Azambuja
Author-email: ricardo.azambuja@gmail.com
License: GPL
Download-URL: https://github.com/thecognifly/YAMSPy/archive/refs/tags/v0.3.3.tar.gz
Keywords: CogniFly,Betaflight,iNAV,drone,UAV,Multi Wii Serial Protocol,MSP
Platform: UNKNOWN
Classifier: Development Status :: 4 - Beta
Classifier: Intended Audience :: Developers
Classifier: Intended Audience :: Education
Classifier: Intended Audience :: Information Technology
Classifier: Intended Audience :: Science/Research
Classifier: License :: OSI Approved :: GNU General Public License v3 (GPLv3)
Classifier: Operating System :: Microsoft :: Windows
Classifier: Operating System :: POSIX :: Linux
Classifier: Programming Language :: Python
Classifier: Framework :: Robot Framework :: Library
Classifier: Topic :: Education
Classifier: Topic :: Scientific/Engineering :: Artificial Intelligence
License-File: LICENSE
